pysalty-0.1.3.dist-info/licenses/LICENSE
salt/__init__.py
salt/core.py
salt/theme.py
pysalty-0.1.3.dist-info/METADATA
pysalty-0.1.3.dist-info/WHEEL
pysalty-0.1.3.dist-info/top_level.txt
pysalty-0.1.3.dist-info/RECORD
