Metadata-Version: 2.4
Name: pysalty
Version: 0.1.3
Summary: PySalty(Python Structural Architecture Layout Tool), publication-ready PyTorch model visualization library
Author: Vyom N. Patel
License: MIT
Project-URL: Homepage, https://github.com/Vyomie/PySalty
Project-URL: Repository, https://github.com/Vyomie/PySalty
Requires-Python: >=3.9
License-File: LICENSE
Requires-Dist: torch
Requires-Dist: matplotlib
Requires-Dist: Pillow
Dynamic: license-file
